{
    "name": "Seer (Medium)",
    "type": "npc",
    "sections": [
        {
            "name": "Description",
            "type": "section",
            "html": "A medium is a speaker who bridges the worlds of the living and the dead. She proclaims rest and blesses gravesites, ushering in birth and consigning the dead to the ground, yet it is also her seance that recalls the shades of the lost and ensures the continuity of a community\u2019s past, present, and future.<br/><br/>A medium could be a village priestess or wise woman, or can simply be used as a generic wandering cleric, or one of many low-to-mid-level priests staff ing a temple.<br/><br/>A medium might be accompanied by two acolytes or a doomsayer (CR 5), or two cultists (CR 6). A medium and hedge wizard (CR 6), hermit (CR 7), or conjurist (CR 7) could preside over a forest oracle or be traveling mendicant mystics. A medium and two acolytes might accompany a priest (CR 9), while five or six mediums could form the entourage for a saint (CR 12) or high priest (CR 13)."
        }
    ],
    "game-obj": "NPCs",
    "stat_block": {
        "name": "Seer (Medium)",
        "type": "stat_block",
        "initiative": {
            "type": "stat_block_section",
            "subtype": "initiative",
            "value": 1
        },
        "perception": [
            {
                "type": "stat_block_section",
                "subtype": "perception",
                "value": 8
            }
        ],
        "senses": [],
        "creature_type": {
            "type": "stat_block_section",
            "subtype": "creature_type",
            "creature_type": "Humanoid",
            "size": "Medium",
            "alignment": "Neutral",
            "alignment_text": "N",
            "cr": "4",
            "xp": 1200,
            "grafts": [
                {
                    "type": "stat_block_section",
                    "subtype": "graft",
                    "name": "Human"
                },
                {
                    "type": "stat_block_section",
                    "subtype": "graft",
                    "name": "cleric 5"
                }
            ]
        },
        "defense": {
            "name": "Defense",
            "type": "stat_block_section",
            "subtype": "defense",
            "ac": {
                "name": "AC",
                "type": "stat_block_section",
                "subtype": "armor_class",
                "ac": 21,
                "touch": 11,
                "flat-footed": 20,
                "modifiers": [
                    {
                        "type": "stat_block_section",
                        "subtype": "modifier",
                        "name": "+7 armor"
                    },
                    {
                        "type": "stat_block_section",
                        "subtype": "modifier",
                        "name": "+1 Dex"
                    },
                    {
                        "type": "stat_block_section",
                        "subtype": "modifier",
                        "name": "+3 shield"
                    }
                ]
            },
            "saves": {
                "type": "stat_block_section",
                "subtype": "saves",
                "fort": {
                    "name": "Fort",
                    "type": "stat_block_section",
                    "subtype": "save",
                    "value": 5
                },
                "ref": {
                    "name": "Ref",
                    "type": "stat_block_section",
                    "subtype": "save",
                    "value": 3
                },
                "will": {
                    "name": "Will",
                    "type": "stat_block_section",
                    "subtype": "save",
                    "value": 8
                }
            }
        },
        "offense": {
            "name": "Offense",
            "type": "stat_block_section",
            "subtype": "offense",
            "speed": {
                "name": "Speed",
                "type": "stat_block_section",
                "subtype": "speeds",
                "movement": [
                    {
                        "type": "stat_block_section",
                        "subtype": "speed",
                        "name": "20 ft.",
                        "movement_type": "walk",
                        "value": 20
                    }
                ]
            },
            "melee": [
                {
                    "type": "stat_block_section",
                    "subtype": "attack",
                    "attack_type": "melee",
                    "name": "light mace",
                    "bonus": [
                        2
                    ],
                    "damage": [
                        {
                            "type": "stat_block_section",
                            "subtype": "attack_damage",
                            "formula": "1d6\u20131"
                        }
                    ]
                }
            ],
            "ranged": [
                {
                    "type": "stat_block_section",
                    "subtype": "attack",
                    "attack_type": "ranged",
                    "name": "dart",
                    "bonus": [
                        4
                    ],
                    "damage": [
                        {
                            "type": "stat_block_section",
                            "subtype": "attack_damage",
                            "formula": "1d4\u20131"
                        }
                    ]
                }
            ],
            "special_attacks": [
                {
                    "type": "stat_block_section",
                    "subtype": "special_attack",
                    "modifiers": [
                        {
                            "type": "stat_block_section",
                            "subtype": "modifier",
                            "name": "DC 14"
                        },
                        {
                            "type": "stat_block_section",
                            "subtype": "modifier",
                            "name": "3d6"
                        }
                    ],
                    "name": "channel positive energy 7/day"
                }
            ],
            "magic": {
                "name": "Magic",
                "type": "stat_block_section",
                "subtype": "magic",
                "spells": [
                    {
                        "name": "Spell-Like Abilities",
                        "type": "stat_block_section",
                        "subtype": "spells",
                        "spell_list": [
                            {
                                "type": "stat_block_section",
                                "subtype": "spell_list",
                                "spells": [
                                    {
                                        "type": "stat_block_section",
                                        "subtype": "spell",
                                        "name": "calming touch (1d6+5 nonlethal)"
                                    },
                                    {
                                        "type": "stat_block_section",
                                        "subtype": "spell",
                                        "name": "gentle rest"
                                    }
                                ],
                                "count_text": "6/day",
                                "count": 6,
                                "frequency": "day"
                            }
                        ],
                        "caster_level": 5,
                        "concentration": 8
                    },
                    {
                        "name": "Cleric Spells Prepared",
                        "type": "stat_block_section",
                        "subtype": "spells",
                        "spell_list": [
                            {
                                "type": "stat_block_section",
                                "subtype": "spell_list",
                                "spells": [
                                    {
                                        "type": "stat_block_section",
                                        "subtype": "spell",
                                        "name": "bestow curse",
                                        "saving_throw": {
                                            "type": "stat_block_section",
                                            "subtype": "save_dc",
                                            "text": "DC 16",
                                            "dc": 16
                                        }
                                    },
                                    {
                                        "type": "stat_block_section",
                                        "subtype": "spell",
                                        "name": "helping hand"
                                    },
                                    {
                                        "type": "stat_block_section",
                                        "subtype": "spell",
                                        "name": "speak with dead",
                                        "notation": "D"
                                    }
                                ],
                                "count_text": "3rd",
                                "frequency": "3rd"
                            },
                            {
                                "type": "stat_block_section",
                                "subtype": "spell_list",
                                "spells": [
                                    {
                                        "type": "stat_block_section",
                                        "subtype": "spell",
                                        "name": "augury"
                                    },
                                    {
                                        "type": "stat_block_section",
                                        "subtype": "spell",
                                        "name": "gentle repose",
                                        "notation": "D"
                                    },
                                    {
                                        "type": "stat_block_section",
                                        "subtype": "spell",
                                        "name": "silence",
                                        "saving_throw": {
                                            "type": "stat_block_section",
                                            "subtype": "save_dc",
                                            "text": "DC 15",
                                            "dc": 15
                                        }
                                    },
                                    {
                                        "type": "stat_block_section",
                                        "subtype": "spell",
                                        "name": "spiritual weapon"
                                    }
                                ],
                                "count_text": "2nd",
                                "frequency": "2nd"
                            },
                            {
                                "type": "stat_block_section",
                                "subtype": "spell_list",
                                "spells": [
                                    {
                                        "type": "stat_block_section",
                                        "subtype": "spell",
                                        "name": "bless"
                                    },
                                    {
                                        "type": "stat_block_section",
                                        "subtype": "spell",
                                        "name": "command",
                                        "saving_throw": {
                                            "type": "stat_block_section",
                                            "subtype": "save_dc",
                                            "text": "DC 14",
                                            "dc": 14
                                        }
                                    },
                                    {
                                        "type": "stat_block_section",
                                        "subtype": "spell",
                                        "name": "comprehend languages"
                                    },
                                    {
                                        "type": "stat_block_section",
                                        "subtype": "spell",
                                        "name": "deathwatch",
                                        "notation": "D"
                                    },
                                    {
                                        "type": "stat_block_section",
                                        "subtype": "spell",
                                        "name": "sanctuary",
                                        "saving_throw": {
                                            "type": "stat_block_section",
                                            "subtype": "save_dc",
                                            "text": "DC 14",
                                            "dc": 14
                                        }
                                    }
                                ],
                                "count_text": "1st",
                                "frequency": "1st"
                            },
                            {
                                "type": "stat_block_section",
                                "subtype": "spell_list",
                                "spells": [
                                    {
                                        "type": "stat_block_section",
                                        "subtype": "spell",
                                        "name": "detect magic"
                                    },
                                    {
                                        "type": "stat_block_section",
                                        "subtype": "spell",
                                        "name": "guidance"
                                    },
                                    {
                                        "type": "stat_block_section",
                                        "subtype": "spell",
                                        "name": "light"
                                    },
                                    {
                                        "type": "stat_block_section",
                                        "subtype": "spell",
                                        "name": "read magic"
                                    }
                                ],
                                "level_text": "0",
                                "level": 0,
                                "count_text": "at will",
                                "frequency": "at will"
                            }
                        ],
                        "caster_level": 5,
                        "concentration": 8
                    }
                ],
                "notations": [
                    {
                        "name": "D",
                        "type": "stat_block_section",
                        "subtype": "notation",
                        "value": "domain spell"
                    }
                ],
                "class_selections": [
                    {
                        "name": "Domains",
                        "type": "stat_block_section",
                        "subtype": "class_selection",
                        "values": [
                            "Community",
                            "Repose"
                        ]
                    }
                ]
            },
            "bab": {
                "type": "stat_block_section",
                "subtype": "bab",
                "value": 3
            },
            "cmb": {
                "type": "stat_block_section",
                "subtype": "cmb",
                "value": 2
            },
            "cmd": {
                "type": "stat_block_section",
                "subtype": "cmd",
                "value": 13
            }
        },
        "gear": [
            {
                "type": "stat_block_section",
                "subtype": "item",
                "name": "+1 chainmail"
            },
            {
                "type": "stat_block_section",
                "subtype": "item",
                "name": "heavy wooden shield"
            },
            {
                "type": "stat_block_section",
                "subtype": "item",
                "name": "light mace"
            },
            {
                "type": "stat_block_section",
                "subtype": "item",
                "name": "darts",
                "quantity": 2
            },
            {
                "type": "stat_block_section",
                "subtype": "item",
                "name": "cloak of resistance +1"
            },
            {
                "type": "stat_block_section",
                "subtype": "item",
                "name": "silver holy symbol"
            },
            {
                "type": "stat_block_section",
                "subtype": "item",
                "name": "augury focus"
            }
        ],
        "boon": "A medium can cast <i>augury</i>, <i>speak with dead</i>, or <i>gentle repose</i> at no charge, or magical healing at a 10% discount.",
        "statistics": {
            "type": "stat_block_section",
            "subtype": "statistics",
            "str": 8,
            "dex": 12,
            "con": 10,
            "int": 14,
            "wis": 17,
            "cha": 14,
            "feats": [
                {
                    "type": "stat_block_section",
                    "subtype": "feat",
                    "name": "Alertness",
                    "link": {
                        "type": "link",
                        "name": "Alertness",
                        "alt": "Alertness",
                        "href": "FeatDisplay.aspx?ItemName=Alertness"
                    }
                },
                {
                    "type": "stat_block_section",
                    "subtype": "feat",
                    "name": "Extra Channel",
                    "link": {
                        "type": "link",
                        "name": "Extra Channel",
                        "alt": "Extra Channel",
                        "href": "FeatDisplay.aspx?ItemName=Extra%20Channel"
                    }
                },
                {
                    "type": "stat_block_section",
                    "subtype": "feat",
                    "name": "Shield Focus",
                    "link": {
                        "type": "link",
                        "name": "Shield Focus",
                        "alt": "Shield Focus",
                        "href": "FeatDisplay.aspx?ItemName=Shield%20Focus"
                    }
                },
                {
                    "type": "stat_block_section",
                    "subtype": "feat",
                    "name": "Turn Undead",
                    "link": {
                        "type": "link",
                        "name": "Turn Undead",
                        "alt": "Turn Undead",
                        "href": "FeatDisplay.aspx?ItemName=Turn%20Undead"
                    }
                }
            ],
            "skills": {
                "type": "stat_block_section",
                "subtype": "skills",
                "skills": [
                    {
                        "type": "stat_block_section",
                        "subtype": "skill",
                        "name": "Diplomacy",
                        "value": 10
                    },
                    {
                        "type": "stat_block_section",
                        "subtype": "skill",
                        "name": "Heal",
                        "value": 11
                    },
                    {
                        "type": "stat_block_section",
                        "subtype": "skill",
                        "name": "Knowledge (planes)",
                        "value": 9
                    },
                    {
                        "type": "stat_block_section",
                        "subtype": "skill",
                        "name": "Knowledge (religion)",
                        "value": 9
                    },
                    {
                        "type": "stat_block_section",
                        "subtype": "skill",
                        "name": "Perception",
                        "value": 8
                    },
                    {
                        "type": "stat_block_section",
                        "subtype": "skill",
                        "name": "Profession (midwife)",
                        "value": 9
                    },
                    {
                        "type": "stat_block_section",
                        "subtype": "skill",
                        "name": "Sense Motive",
                        "value": 13
                    },
                    {
                        "type": "stat_block_section",
                        "subtype": "skill",
                        "name": "Spellcraft",
                        "value": 6
                    }
                ]
            },
            "languages": {
                "type": "stat_block_section",
                "subtype": "languages",
                "languages": [
                    {
                        "type": "stat_block_section",
                        "subtype": "language",
                        "name": "Celestial"
                    },
                    {
                        "type": "stat_block_section",
                        "subtype": "language",
                        "name": "Common"
                    },
                    {
                        "type": "stat_block_section",
                        "subtype": "language",
                        "name": "Infernal"
                    }
                ]
            }
        }
    },
    "sources": [
        {
            "type": "source",
            "name": "GameMastery Guide",
            "link": {
                "type": "link",
                "name": "GameMastery Guide pg. 299",
                "alt": "GameMastery Guide pg. 299",
                "href": "http://paizo.com/pathfinderRPG/v5748btpy8ffn"
            },
            "page": 299
        }
    ]
}