{
    "name": "Cythnigot",
    "type": "monster",
    "sections": [
        {
            "name": "Ecology",
            "type": "section",
            "html": "<b>Environment</b> any (Abyss)<br/><b>Organization</b> solitary or bloom (2\u201312)<br/><b>Treasure</b> standard"
        },
        {
            "name": "Special Abilities",
            "type": "section",
            "html": "<b>Horrific Appearance (Su)</b> Creatures that succumb to a cythnigot\u2019s horrific appearance become sickened for 1 round\u2014a cythnigot\u2019s horrific appearance only functions to a range of 10 feet. Once a creature makes a saving throw against a particular cythnigot\u2019s horrific appearance, that creature is immune to the horrific appearance of all cythnigots for 24 hours. A spellcaster that has a cythnigot as a familiar is immune to the horrific appearance of all cythnigots, and also gains a +4 bonus on saving throws made against any qlippoth\u2019s horrific appearance.<br/><br/><b>Spores (Su) </b>Any creature bitten by a cythnigot must make a DC 11 Fortitude save or become infested by the creature\u2019s otherworldly spores. These spores cause twitching spikes and hideous pallid growths of hair-like fibers to erupt from the bite wound and to writhe and wrap around the target\u2019s limbs. A creature suffering from these spores is entangled, and can attempt a new DC 11 Fortitude save in later rounds as a standard action to rip the tendrils free and escape the entangled condition. The effects of multiple cythnigot bites on a creature do not stack. Plant creatures take a \u20134 penalty on saves against this effect. This is a disease effect. The save DC is Constitution-based."
        },
        {
            "name": "Description",
            "type": "section",
            "html": "The cythnigot is a foul fungal parasite that grows and thrives within the corpses of small animals. The fungus transforms the host corpse in hideous ways, adding legs or rearranging features\u2014a rat might gain an extra pair of legs and an insectoid visage, while a cat could lose all its legs and fur and gain a snake-like body. The only thing that all cythnigots have in common is a long stalk of fungal material that extends up from the creature\u2019s body, ending in a surprisingly strong set of fanged jaws. A cythnigot without a host body appears as little more than a foul-smelling puffball the size of a human\u2019s fist.<br/><br/>Chaotic evil spellcasters of caster level 7th who have the Improved Familiar feat can gain a cythnigot as a familiar\u2014to do so, the spellcaster must already have a Tiny animal as a familiar. Infusing this familiar with the spores results in a cythnigot that is a loyal, if rather disgusting, minion of the spellcaster.<br/><br/>A cythnigot is about 20 inches long and weighs 10 pounds."
        }
    ],
    "html": "<i>This six-legged horror has a spider\u2019s face and a fibrous stalk growing out of its back\u2014a stalk ending in a snapping mouth.</i>",
    "game-obj": "Monsters",
    "stat_block": {
        "name": "Cythnigot",
        "type": "stat_block",
        "initiative": {
            "type": "stat_block_section",
            "subtype": "initiative",
            "value": 1
        },
        "perception": [
            {
                "type": "stat_block_section",
                "subtype": "perception",
                "value": 5
            }
        ],
        "senses": [
            {
                "type": "stat_block_section",
                "subtype": "sense",
                "name": "darkvision 60 ft."
            },
            {
                "type": "stat_block_section",
                "subtype": "sense",
                "name": "detect law"
            },
            {
                "type": "stat_block_section",
                "subtype": "sense",
                "name": "detect magic"
            }
        ],
        "creature_type": {
            "type": "stat_block_section",
            "subtype": "creature_type",
            "creature_type": "Outsider",
            "creature_subtypes": [
                {
                    "type": "stat_block_section",
                    "subtype": "creature_subtype",
                    "name": "chaotic"
                },
                {
                    "type": "stat_block_section",
                    "subtype": "creature_subtype",
                    "name": "evil"
                },
                {
                    "type": "stat_block_section",
                    "subtype": "creature_subtype",
                    "name": "extraplanar"
                },
                {
                    "type": "stat_block_section",
                    "subtype": "creature_subtype",
                    "name": "qlippoth"
                }
            ],
            "size": "Tiny",
            "alignment": "Chaotic Evil",
            "alignment_text": "CE",
            "family": "Qlippoth",
            "cr": "2",
            "xp": 600
        },
        "defense": {
            "name": "Defense",
            "type": "stat_block_section",
            "subtype": "defense",
            "ac": {
                "name": "AC",
                "type": "stat_block_section",
                "subtype": "armor_class",
                "ac": 14,
                "touch": 13,
                "flat-footed": 13,
                "modifiers": [
                    {
                        "type": "stat_block_section",
                        "subtype": "modifier",
                        "name": "+1 Dex"
                    },
                    {
                        "type": "stat_block_section",
                        "subtype": "modifier",
                        "name": "+1 natural"
                    },
                    {
                        "type": "stat_block_section",
                        "subtype": "modifier",
                        "name": "+2 size"
                    }
                ]
            },
            "saves": {
                "type": "stat_block_section",
                "subtype": "saves",
                "fort": {
                    "name": "Fort",
                    "type": "stat_block_section",
                    "subtype": "save",
                    "value": 1
                },
                "ref": {
                    "name": "Ref",
                    "type": "stat_block_section",
                    "subtype": "save",
                    "value": 6
                },
                "will": {
                    "name": "Will",
                    "type": "stat_block_section",
                    "subtype": "save",
                    "value": 2
                }
            },
            "dr": [
                {
                    "type": "stat_block_section",
                    "subtype": "dr",
                    "value": 5,
                    "text": "5/cold iron or lawful",
                    "conjunction": "or",
                    "damage_types": [
                        "cold iron",
                        "lawful"
                    ]
                }
            ],
            "immunities": [
                {
                    "type": "stat_block_section",
                    "subtype": "immunity",
                    "name": "cold"
                },
                {
                    "type": "stat_block_section",
                    "subtype": "immunity",
                    "name": "poison"
                },
                {
                    "type": "stat_block_section",
                    "subtype": "immunity",
                    "name": "mind-affecting effects"
                }
            ],
            "resistances": [
                {
                    "type": "stat_block_section",
                    "subtype": "resistance",
                    "value": 10,
                    "name": "acid"
                },
                {
                    "type": "stat_block_section",
                    "subtype": "resistance",
                    "value": 10,
                    "name": "electricity"
                },
                {
                    "type": "stat_block_section",
                    "subtype": "resistance",
                    "value": 10,
                    "name": "fire"
                }
            ]
        },
        "offense": {
            "name": "Offense",
            "type": "stat_block_section",
            "subtype": "offense",
            "speed": {
                "name": "Speed",
                "type": "stat_block_section",
                "subtype": "speeds",
                "movement": [
                    {
                        "type": "stat_block_section",
                        "subtype": "speed",
                        "name": "40 ft.",
                        "movement_type": "walk",
                        "value": 40
                    },
                    {
                        "type": "stat_block_section",
                        "subtype": "speed",
                        "modifiers": [
                            {
                                "type": "stat_block_section",
                                "subtype": "modifier",
                                "name": "good<br/>"
                            }
                        ],
                        "name": "fly 60 ft.",
                        "movement_type": "fly",
                        "value": 60
                    }
                ]
            },
            "melee": [
                {
                    "type": "stat_block_section",
                    "subtype": "attack",
                    "attack_type": "melee",
                    "name": "bite",
                    "bonus": [
                        6
                    ],
                    "damage": [
                        {
                            "type": "stat_block_section",
                            "subtype": "attack_damage",
                            "formula": "1d6+1"
                        },
                        {
                            "type": "stat_block_section",
                            "subtype": "attack_damage",
                            "effect": "spores"
                        }
                    ]
                }
            ],
            "space": "2-1/2 ft.",
            "reach": {
                "type": "stat_block_section",
                "subtype": "reach",
                "value": "0 ft."
            },
            "special_attacks": [
                {
                    "type": "stat_block_section",
                    "subtype": "special_attack",
                    "modifiers": [
                        {
                            "type": "stat_block_section",
                            "subtype": "modifier",
                            "name": "10 feet"
                        },
                        {
                            "type": "stat_block_section",
                            "subtype": "modifier",
                            "name": "DC 9"
                        }
                    ],
                    "name": "horrific appearance"
                }
            ],
            "magic": {
                "name": "Magic",
                "type": "stat_block_section",
                "subtype": "magic",
                "spells": [
                    {
                        "name": "Spell-Like Abilities",
                        "type": "stat_block_section",
                        "subtype": "spells",
                        "spell_list": [
                            {
                                "type": "stat_block_section",
                                "subtype": "spell_list",
                                "spells": [
                                    {
                                        "type": "stat_block_section",
                                        "subtype": "spell",
                                        "name": "detect law"
                                    },
                                    {
                                        "type": "stat_block_section",
                                        "subtype": "spell",
                                        "name": "detect magic"
                                    },
                                    {
                                        "type": "stat_block_section",
                                        "subtype": "spell",
                                        "name": "fly"
                                    }
                                ],
                                "count_text": "Constant",
                                "frequency": "Constant"
                            },
                            {
                                "type": "stat_block_section",
                                "subtype": "spell_list",
                                "spells": [
                                    {
                                        "type": "stat_block_section",
                                        "subtype": "spell",
                                        "name": "soften earth and stone"
                                    },
                                    {
                                        "type": "stat_block_section",
                                        "subtype": "spell",
                                        "name": "warp wood"
                                    }
                                ],
                                "count_text": "1/day",
                                "count": 1,
                                "frequency": "day"
                            },
                            {
                                "type": "stat_block_section",
                                "subtype": "spell_list",
                                "spells": [
                                    {
                                        "type": "stat_block_section",
                                        "subtype": "spell",
                                        "name": "commune",
                                        "modifiers": [
                                            {
                                                "type": "stat_block_section",
                                                "subtype": "modifier",
                                                "name": "six questions"
                                            }
                                        ]
                                    }
                                ],
                                "count_text": "1/week",
                                "count": 1,
                                "frequency": "week"
                            }
                        ],
                        "caster_level": 6,
                        "concentration": 4
                    }
                ]
            },
            "bab": {
                "type": "stat_block_section",
                "subtype": "bab",
                "value": 3
            },
            "cmb": {
                "type": "stat_block_section",
                "subtype": "cmb",
                "value": 2
            },
            "cmd": {
                "type": "stat_block_section",
                "subtype": "cmd",
                "modifiers": [
                    {
                        "type": "stat_block_section",
                        "subtype": "modifier",
                        "name": "21 vs. trip"
                    }
                ],
                "value": 13
            }
        },
        "statistics": {
            "type": "stat_block_section",
            "subtype": "statistics",
            "str": 12,
            "dex": 12,
            "con": 11,
            "int": 11,
            "wis": 8,
            "cha": 7,
            "feats": [
                {
                    "type": "stat_block_section",
                    "subtype": "feat",
                    "name": "Lightning Reflexes",
                    "link": {
                        "type": "link",
                        "name": "Lightning Reflexes",
                        "alt": "Lightning Reflexes",
                        "href": "FeatDisplay.aspx?ItemName=Lightning%20Reflexes"
                    }
                },
                {
                    "type": "stat_block_section",
                    "subtype": "feat",
                    "name": "Weapon Finesse",
                    "link": {
                        "type": "link",
                        "name": "Weapon Finesse",
                        "alt": "Weapon Finesse",
                        "href": "FeatDisplay.aspx?ItemName=Weapon%20Finesse"
                    }
                }
            ],
            "skills": {
                "type": "stat_block_section",
                "subtype": "skills",
                "skills": [
                    {
                        "type": "stat_block_section",
                        "subtype": "skill",
                        "name": "Acrobatics",
                        "value": 7,
                        "modifiers": [
                            {
                                "type": "stat_block_section",
                                "subtype": "modifier",
                                "name": "+11 jump"
                            }
                        ]
                    },
                    {
                        "type": "stat_block_section",
                        "subtype": "skill",
                        "name": "Fly",
                        "value": 15
                    },
                    {
                        "type": "stat_block_section",
                        "subtype": "skill",
                        "name": "Knowledge (nature)",
                        "value": 6
                    },
                    {
                        "type": "stat_block_section",
                        "subtype": "skill",
                        "name": "Knowledge (planes)",
                        "value": 6
                    },
                    {
                        "type": "stat_block_section",
                        "subtype": "skill",
                        "name": "Perception",
                        "value": 5
                    },
                    {
                        "type": "stat_block_section",
                        "subtype": "skill",
                        "name": "Stealth",
                        "value": 15
                    }
                ]
            },
            "languages": {
                "type": "stat_block_section",
                "subtype": "languages",
                "languages": [
                    {
                        "type": "stat_block_section",
                        "subtype": "language",
                        "name": "Abyssal"
                    }
                ],
                "communication_abilities": [
                    {
                        "type": "stat_block_section",
                        "subtype": "communication_ability",
                        "modifiers": [
                            {
                                "type": "stat_block_section",
                                "subtype": "modifier",
                                "name": "touch"
                            }
                        ],
                        "name": "telepathy"
                    }
                ]
            }
        }
    },
    "sources": [
        {
            "type": "source",
            "name": "Bestiary 2",
            "link": {
                "type": "link",
                "name": "Bestiary 2 pg. 221",
                "alt": "Bestiary 2 pg. 221",
                "href": "http://paizo.com/pathfinderRPG/v5748btpy8hif"
            },
            "page": 221
        }
    ]
}